kore_plugins_motor/__init__.py
kore_plugins_motor/plugins/__init__.py
kore_plugins_motor/plugins/asyncio.py
kore_plugins_motor/plugins/config.py
kore_plugins_motor-0.0.1.dist-info/DESCRIPTION.rst
kore_plugins_motor-0.0.1.dist-info/METADATA
kore_plugins_motor-0.0.1.dist-info/RECORD
kore_plugins_motor-0.0.1.dist-info/WHEEL
kore_plugins_motor-0.0.1.dist-info/entry_points.txt
kore_plugins_motor-0.0.1.dist-info/metadata.json
kore_plugins_motor-0.0.1.dist-info/top_level.txt
